importador_docfis_lib/__init__.py
importador_docfis_lib/controller/__init__.py
importador_docfis_lib/controller/controller_estabelecimento.py
importador_docfis_lib/controller/controller_nfce.py
importador_docfis_lib/dao/__init__.py
importador_docfis_lib/dao/cfop_dao.py
importador_docfis_lib/dao/cliente_dao.py
importador_docfis_lib/dao/estabelecimento_dao.py
importador_docfis_lib/dao/item_nota_dao.py
importador_docfis_lib/dao/lanfis_dao.py
importador_docfis_lib/dao/lf_itens_dao.py
importador_docfis_lib/dao/nfce_dao.py
importador_docfis_lib/dao/operacao_cfop_slot_dao.py
importador_docfis_lib/dao/pagamento_dao.py
importador_docfis_lib/dao/produto_dao.py
importador_docfis_lib/dao/unidade_dao.py
importador_docfis_lib/dto/__init__.py
importador_docfis_lib/dto/cfop.py
importador_docfis_lib/dto/cliente.py
importador_docfis_lib/dto/estabelecimento.py
importador_docfis_lib/dto/operacao_cfop_slot.py
importador_docfis_lib/dto/produto.py
importador_docfis_lib/dto/servico.py
importador_docfis_lib/dto/unidade.py
importador_docfis_lib/dto_handler/__init__.py
importador_docfis_lib/dto_handler/cofins.py
importador_docfis_lib/dto_handler/icms.py
importador_docfis_lib/dto_handler/item_nota.py
importador_docfis_lib/dto_handler/nfce.py
importador_docfis_lib/dto_handler/pagamento.py
importador_docfis_lib/dto_handler/participante.py
importador_docfis_lib/dto_handler/pis.py
importador_docfis_lib/enums/__init__.py
importador_docfis_lib/enums/enum_tipo_documento.py
importador_docfis_lib/handler/__init__.py
importador_docfis_lib/handler/cofins_handler.py
importador_docfis_lib/handler/destinatario_handler.py
importador_docfis_lib/handler/evento_handler.py
importador_docfis_lib/handler/icms_handler.py
importador_docfis_lib/handler/nfce_handler.py
importador_docfis_lib/handler/pis_handler.py
importador_docfis_lib/handler/produto_handler.py
importador_docfis_lib/utils/__init__.py
importador_docfis_lib/utils/conexao_postgres_adapter.py
importador_docfis_lib/utils/lanfis.py
importador_docfis_lib-0.0.7.dist-info/METADATA
importador_docfis_lib-0.0.7.dist-info/WHEEL
importador_docfis_lib-0.0.7.dist-info/top_level.txt
importador_docfis_lib-0.0.7.dist-info/RECORD
